snelstart/__init__.py
snelstart/api.py
snelstart/core.py
snelstart/tests/__init__.py
snelstart/tests/test_snelstart.py
snelstart-0.2.1.dist-info/LICENSE
snelstart-0.2.1.dist-info/METADATA
snelstart-0.2.1.dist-info/WHEEL
snelstart-0.2.1.dist-info/top_level.txt
snelstart-0.2.1.dist-info/RECORD
