Metadata-Version: 2.1
Name: snelstart
Version: 0.2.1
Summary: Package for pulling datasets using the Snelstart API
Home-page: https://github.com/zypp-io/snelstart
Author: Zypp
Author-email: hello@zypp.io
Project-URL: Bug Reports, https://github.com/zypp-io/snelstart/issues
Project-URL: Source, https://github.com/zypp-io/snelstart
Keywords: python,snelstart,API
Classifier: Programming Language :: Python :: 3
Classifier: License :: OSI Approved :: MIT License
Classifier: Operating System :: OS Independent
Requires-Python: >=3.7
License-File: LICENSE
Requires-Dist: pandas
Requires-Dist: requests
